rarce/__init__.py
rarce/__main__.py
rarce/cli.py
rarce/rarce.py
rarce-1.0.0.dist-info/METADATA
rarce-1.0.0.dist-info/WHEEL
rarce-1.0.0.dist-info/entry_points.txt
rarce-1.0.0.dist-info/top_level.txt
rarce-1.0.0.dist-info/RECORD
