Metadata-Version: 2.1
Name: rarce
Version: 1.0.0
Summary: Exploit generator for CVE-2023-38831, WinRAR RCE.
Home-page: UNKNOWN
Author: Ata Hakcil
License: UNKNOWN
Keywords: winrar,exploit,rce,cve-2023-38831
Platform: UNKNOWN
